{
  "page_summary": {
    "document_type": "mixed",
    "main_content": "[서식2 이 력 서]. 가. 공통사항. ※ 담당자 기재",
    "key_entities": {
      "companies": [],
      "dates": [
        "2024.01.01",
        "2024.12.31"
      ],
      "amounts": [],
      "emails": [],
      "phones": [],
      "invoice_numbers": []
    },
    "content_sections": {
      "title": 0,
      "header": 0,
      "body": 0,
      "table": 3,
      "footer": 0,
      "other": 46
    },
    "quality_metrics": {
      "overall_confidence": 0.966,
      "readability": "low",
      "completeness": "complete",
      "high_confidence_blocks": 46,
      "low_confidence_blocks": 1
    },
    "language_distribution": {
      "korean": 0.654,
      "english": 0.01,
      "other": 0.337
    },
    "structural_analysis": {
      "has_header": true,
      "has_footer": true,
      "column_layout": "single",
      "text_alignment": "mixed"
    },
    "total_blocks": 49,
    "total_characters": 467,
    "analyzed_at": "2025-11-28T04:59:38.204158"
  },
  "block_summaries": [
    {
      "content_type": "table",
      "language": "korean",
      "text_preview": "[서식2 이 력 서]",
      "keywords": [
        "서식2"
      ],
      "confidence_level": "medium",
      "estimated_importance": "normal",
      "contains_numbers": false,
      "contains_dates": false,
      "contains_money": false,
      "contains_email": false,
      "contains_phone": false,
      "text_length": 11,
      "word_count": 4,
      "analyzed_at": "2025-11-28T04:59:38.203384"
    },
    {
      "content_type": "number",
      "language": "other",
      "text_preview": "0",
      "keywords": [],
      "confidence_level": "medium",
      "estimated_importance": "important",
      "contains_numbers": true,
      "contains_dates": false,
      "contains_money": false,
      "contains_email": false,
      "contains_phone": false,
      "text_length": 1,
      "word_count": 1,
      "analyzed_at": "2025-11-28T04:59:38.203403"
    },
    {
      "content_type": "other",
      "language": "korean",
      "text_preview": "력 서",
      "keywords": [],
      "confidence_level": "high",
      "estimated_importance": "low",
      "contains_numbers": false,
      "contains_dates": false,
      "contains_money": false,
      "contains_email": false,
      "contains_phone": false,
      "text_length": 3,
      "word_count": 2,
      "analyzed_at": "2025-11-28T04:59:38.203416"
    },
    {
      "content_type": "other",
      "language": "korean",
      "text_preview": "가. 공통사항",
      "keywords": [
        "공통사항"
      ],
      "confidence_level": "high",
      "estimated_importance": "low",
      "contains_numbers": false,
      "contains_dates": false,
      "contains_money": false,
      "contains_email": false,
      "contains_phone": false,
      "text_length": 7,
      "word_count": 2,
      "analyzed_at": "2025-11-28T04:59:38.203429"
    },
    {
      "content_type": "other",
      "language": "korean",
      "text_preview": "※ 담당자 기재",
      "keywords": [
        "담당자"
      ],
      "confidence_level": "high",
      "estimated_importance": "low",
      "contains_numbers": false,
      "contains_dates": false,
      "contains_money": false,
      "contains_email": false,
      "contains_phone": false,
      "text_length": 8,
      "word_count": 3,
      "analyzed_at": "2025-11-28T04:59:38.203447"
    },
    {
      "content_type": "address",
      "language": "korean",
      "text_preview": "응시번호",
      "keywords": [
        "응시번호"
      ],
      "confidence_level": "high",
      "estimated_importance": "important",
      "contains_numbers": false,
      "contains_dates": false,
      "contains_money": false,
      "contains_email": false,
      "contains_phone": false,
      "text_length": 4,
      "word_count": 1,
      "analyzed_at": "2025-11-28T04:59:38.203458"
    },
    {
      "content_type": "other",
      "language": "korean",
      "text_preview": "사",
      "keywords": [],
      "confidence_level": "high",
      "estimated_importance": "low",
      "contains_numbers": false,
      "contains_dates": false,
      "contains_money": false,
      "contains_email": false,
      "contains_phone": false,
      "text_length": 1,
      "word_count": 1,
      "analyzed_at": "2025-11-28T04:59:38.203467"
    },
    {
      "content_type": "other",
      "language": "korean",
      "text_preview": "진",
      "keywords": [],
      "confidence_level": "high",
      "estimated_importance": "low",
      "contains_numbers": false,
      "contains_dates": false,
      "contains_money": false,
      "contains_email": false,
      "contains_phone": false,
      "text_length": 1,
      "word_count": 1,
      "analyzed_at": "2025-11-28T04:59:38.203475"
    },
    {
      "content_type": "address",
      "language": "korean",
      "text_preview": "응시분야",
      "keywords": [
        "응시분야"
      ],
      "confidence_level": "high",
      "estimated_importance": "important",
      "contains_numbers": false,
      "contains_dates": false,
      "contains_money": false,
      "contains_email": false,
      "contains_phone": false,
      "text_length": 4,
      "word_count": 1,
      "analyzed_at": "2025-11-28T04:59:38.203484"
    },
    {
      "content_type": "other",
      "language": "korean",
      "text_preview": "6개월 이내에",
      "keywords": [
        "6개월",
        "이내에"
      ],
      "confidence_level": "high",
      "estimated_importance": "low",
      "contains_numbers": false,
      "contains_dates": false,
      "contains_money": false,
      "contains_email": false,
      "contains_phone": false,
      "text_length": 7,
      "word_count": 2,
      "analyzed_at": "2025-11-28T04:59:38.203498"
    },
    {
      "content_type": "other",
      "language": "korean",
      "text_preview": "촬영한 탈모",
      "keywords": [
        "촬영한"
      ],
      "confidence_level": "high",
      "estimated_importance": "low",
      "contains_numbers": false,
      "contains_dates": false,
      "contains_money": false,
      "contains_email": false,
      "contains_phone": false,
      "text_length": 6,
      "word_count": 2,
      "analyzed_at": "2025-11-28T04:59:38.203509"
    },
    {
      "content_type": "other",
      "language": "korean",
      "text_preview": "상반신",
      "keywords": [
        "상반신"
      ],
      "confidence_level": "high",
      "estimated_importance": "low",
      "contains_numbers": false,
      "contains_dates": false,
      "contains_money": false,
      "contains_email": false,
      "contains_phone": false,
      "text_length": 3,
      "word_count": 1,
      "analyzed_at": "2025-11-28T04:59:38.203518"
    },
    {
      "content_type": "address",
      "language": "korean",
      "text_preview": "응시분야",
      "keywords": [
        "응시분야"
      ],
      "confidence_level": "high",
      "estimated_importance": "important",
      "contains_numbers": false,
      "contains_dates": false,
      "contains_money": false,
      "contains_email": false,
      "contains_phone": false,
      "text_length": 4,
      "word_count": 1,
      "analyzed_at": "2025-11-28T04:59:38.203527"
    },
    {
      "content_type": "other",
      "language": "mixed",
      "text_preview": "사진(3.5Cm×4.5Cm)",
      "keywords": [
        "5cm"
      ],
      "confidence_level": "high",
      "estimated_importance": "low",
      "contains_numbers": true,
      "contains_dates": false,
      "contains_money": false,
      "contains_email": false,
      "contains_phone": false,
      "text_length": 15,
      "word_count": 1,
      "analyzed_at": "2025-11-28T04:59:38.203546"
    },
    {
      "content_type": "other",
      "language": "korean",
      "text_preview": "성 명",
      "keywords": [],
      "confidence_level": "high",
      "estimated_importance": "low",
      "contains_numbers": false,
      "contains_dates": false,
      "contains_money": false,
      "contains_email": false,
      "contains_phone": false,
      "text_length": 3,
      "word_count": 2,
      "analyzed_at": "2025-11-28T04:59:38.203556"
    },
    {
      "content_type": "other",
      "language": "korean",
      "text_preview": "생년월일",
      "keywords": [
        "생년월일"
      ],
      "confidence_level": "high",
      "estimated_importance": "low",
      "contains_numbers": false,
      "contains_dates": false,
      "contains_money": false,
      "contains_email": false,
      "contains_phone": false,
      "text_length": 4,
      "word_count": 1,
      "analyzed_at": "2025-11-28T04:59:38.203565"
    },
    {
      "content_type": "address",
      "language": "korean",
      "text_preview": "나. 응시자격",
      "keywords": [
        "응시자격"
      ],
      "confidence_level": "high",
      "estimated_importance": "important",
      "contains_numbers": false,
      "contains_dates": false,
      "contains_money": false,
      "contains_email": false,
      "contains_phone": false,
      "text_length": 7,
      "word_count": 2,
      "analyzed_at": "2025-11-28T04:59:38.203577"
    },
    {
      "content_type": "other",
      "language": "korean",
      "text_preview": "자격 증명",
      "keywords": [],
      "confidence_level": "high",
      "estimated_importance": "low",
      "contains_numbers": false,
      "contains_dates": false,
      "contains_money": false,
      "contains_email": false,
      "contains_phone": false,
      "text_length": 5,
      "word_count": 2,
      "analyzed_at": "2025-11-28T04:59:38.203587"
    },
    {
      "content_type": "other",
      "language": "korean",
      "text_preview": "등록번호 / 자격증 취득(예정)일",
      "keywords": [
        "등록번호",
        "자격증"
      ],
      "confidence_level": "high",
      "estimated_importance": "important",
      "contains_numbers": false,
      "contains_dates": false,
      "contains_money": false,
      "contains_email": false,
      "contains_phone": false,
      "text_length": 18,
      "word_count": 4,
      "analyzed_at": "2025-11-28T04:59:38.203603"
    },
    {
      "content_type": "other",
      "language": "korean",
      "text_preview": "자격 검정기관",
      "keywords": [
        "검정기관"
      ],
      "confidence_level": "high",
      "estimated_importance": "low",
      "contains_numbers": false,
      "contains_dates": false,
      "contains_money": false,
      "contains_email": false,
      "contains_phone": false,
      "text_length": 7,
      "word_count": 2,
      "analyzed_at": "2025-11-28T04:59:38.203613"
    },
    {
      "content_type": "other",
      "language": "korean",
      "text_preview": "자",
      "keywords": [],
      "confidence_level": "high",
      "estimated_importance": "low",
      "contains_numbers": false,
      "contains_dates": false,
      "contains_money": false,
      "contains_email": false,
      "contains_phone": false,
      "text_length": 1,
      "word_count": 1,
      "analyzed_at": "2025-11-28T04:59:38.203622"
    },
    {
      "content_type": "other",
      "language": "korean",
      "text_preview": "격",
      "keywords": [],
      "confidence_level": "high",
      "estimated_importance": "low",
      "contains_numbers": false,
      "contains_dates": false,
      "contains_money": false,
      "contains_email": false,
      "contains_phone": false,
      "text_length": 1,
      "word_count": 1,
      "analyzed_at": "2025-11-28T04:59:38.203630"
    },
    {
      "content_type": "other",
      "language": "korean",
      "text_preview": "증",
      "keywords": [],
      "confidence_level": "high",
      "estimated_importance": "low",
      "contains_numbers": false,
      "contains_dates": false,
      "contains_money": false,
      "contains_email": false,
      "contains_phone": false,
      "text_length": 1,
      "word_count": 1,
      "analyzed_at": "2025-11-28T04:59:38.203638"
    },
    {
      "content_type": "other",
      "language": "korean",
      "text_preview": "근 무 기 관",
      "keywords": [],
      "confidence_level": "high",
      "estimated_importance": "low",
      "contains_numbers": false,
      "contains_dates": false,
      "contains_money": false,
      "contains_email": false,
      "contains_phone": false,
      "text_length": 7,
      "word_count": 4,
      "analyzed_at": "2025-11-28T04:59:38.203649"
    },
    {
      "content_type": "other",
      "language": "korean",
      "text_preview": "근 무 기 간",
      "keywords": [],
      "confidence_level": "high",
      "estimated_importance": "low",
      "contains_numbers": false,
      "contains_dates": false,
      "contains_money": false,
      "contains_email": false,
      "contains_phone": false,
      "text_length": 7,
      "word_count": 4,
      "analyzed_at": "2025-11-28T04:59:38.203659"
    },
    {
      "content_type": "other",
      "language": "korean",
      "text_preview": "직 위",
      "keywords": [],
      "confidence_level": "high",
      "estimated_importance": "low",
      "contains_numbers": false,
      "contains_dates": false,
      "contains_money": false,
      "contains_email": false,
      "contains_phone": false,
      "text_length": 3,
      "word_count": 2,
      "analyzed_at": "2025-11-28T04:59:38.203668"
    },
    {
      "content_type": "other",
      "language": "korean",
      "text_preview": "담 당 업 무",
      "keywords": [],
      "confidence_level": "high",
      "estimated_importance": "low",
      "contains_numbers": false,
      "contains_dates": false,
      "contains_money": false,
      "contains_email": false,
      "contains_phone": false,
      "text_length": 7,
      "word_count": 4,
      "analyzed_at": "2025-11-28T04:59:38.203678"
    },
    {
      "content_type": "other",
      "language": "korean",
      "text_preview": "비고",
      "keywords": [],
      "confidence_level": "high",
      "estimated_importance": "low",
      "contains_numbers": false,
      "contains_dates": false,
      "contains_money": false,
      "contains_email": false,
      "contains_phone": false,
      "text_length": 2,
      "word_count": 1,
      "analyzed_at": "2025-11-28T04:59:38.203686"
    },
    {
      "content_type": "other",
      "language": "korean",
      "text_preview": "(부 서 포 함)",
      "keywords": [],
      "confidence_level": "high",
      "estimated_importance": "low",
      "contains_numbers": false,
      "contains_dates": false,
      "contains_money": false,
      "contains_email": false,
      "contains_phone": false,
      "text_length": 9,
      "word_count": 4,
      "analyzed_at": "2025-11-28T04:59:38.203698"
    },
    {
      "content_type": "other",
      "language": "korean",
      "text_preview": "예)상근",
      "keywords": [],
      "confidence_level": "high",
      "estimated_importance": "low",
      "contains_numbers": false,
      "contains_dates": false,
      "contains_money": false,
      "contains_email": false,
      "contains_phone": false,
      "text_length": 4,
      "word_count": 1,
      "analyzed_at": "2025-11-28T04:59:38.203707"
    },
    {
      "content_type": "table",
      "language": "other",
      "text_preview": "2024.01.01. ~ 2024.12.31.",
      "keywords": [
        "2024"
      ],
      "confidence_level": "low",
      "estimated_importance": "normal",
      "contains_numbers": true,
      "contains_dates": true,
      "contains_money": false,
      "contains_email": false,
      "contains_phone": false,
      "text_length": 25,
      "word_count": 3,
      "analyzed_at": "2025-11-28T04:59:38.203728"
    },
    {
      "content_type": "other",
      "language": "korean",
      "text_preview": "사원",
      "keywords": [],
      "confidence_level": "high",
      "estimated_importance": "low",
      "contains_numbers": false,
      "contains_dates": false,
      "contains_money": false,
      "contains_email": false,
      "contains_phone": false,
      "text_length": 2,
      "word_count": 1,
      "analyzed_at": "2025-11-28T04:59:38.203737"
    },
    {
      "content_type": "other",
      "language": "korean",
      "text_preview": "경",
      "keywords": [],
      "confidence_level": "high",
      "estimated_importance": "low",
      "contains_numbers": false,
      "contains_dates": false,
      "contains_money": false,
      "contains_email": false,
      "contains_phone": false,
      "text_length": 1,
      "word_count": 1,
      "analyzed_at": "2025-11-28T04:59:38.203746"
    },
    {
      "content_type": "address",
      "language": "korean",
      "text_preview": "예)주30시",
      "keywords": [
        "주30시"
      ],
      "confidence_level": "medium",
      "estimated_importance": "important",
      "contains_numbers": false,
      "contains_dates": false,
      "contains_money": false,
      "contains_email": false,
      "contains_phone": false,
      "text_length": 6,
      "word_count": 1,
      "analyzed_at": "2025-11-28T04:59:38.203757"
    },
    {
      "content_type": "other",
      "language": "korean",
      "text_preview": "※임용분야와 관련된",
      "keywords": [
        "임용분야와",
        "관련된"
      ],
      "confidence_level": "high",
      "estimated_importance": "low",
      "contains_numbers": false,
      "contains_dates": false,
      "contains_money": false,
      "contains_email": false,
      "contains_phone": false,
      "text_length": 10,
      "word_count": 2,
      "analyzed_at": "2025-11-28T04:59:38.203770"
    },
    {
      "content_type": "other",
      "language": "korean",
      "text_preview": "팀장",
      "keywords": [],
      "confidence_level": "high",
      "estimated_importance": "low",
      "contains_numbers": false,
      "contains_dates": false,
      "contains_money": false,
      "contains_email": false,
      "contains_phone": false,
      "text_length": 2,
      "word_count": 1,
      "analyzed_at": "2025-11-28T04:59:38.203778"
    },
    {
      "content_type": "other",
      "language": "korean",
      "text_preview": "경력만 작성",
      "keywords": [
        "경력만"
      ],
      "confidence_level": "high",
      "estimated_importance": "low",
      "contains_numbers": false,
      "contains_dates": false,
      "contains_money": false,
      "contains_email": false,
      "contains_phone": false,
      "text_length": 6,
      "word_count": 2,
      "analyzed_at": "2025-11-28T04:59:38.203788"
    },
    {
      "content_type": "other",
      "language": "korean",
      "text_preview": "간",
      "keywords": [],
      "confidence_level": "low",
      "estimated_importance": "low",
      "contains_numbers": false,
      "contains_dates": false,
      "contains_money": false,
      "contains_email": false,
      "contains_phone": false,
      "text_length": 1,
      "word_count": 1,
      "analyzed_at": "2025-11-28T04:59:38.203796"
    },
    {
      "content_type": "other",
      "language": "korean",
      "text_preview": "력",
      "keywords": [],
      "confidence_level": "medium",
      "estimated_importance": "low",
      "contains_numbers": false,
      "contains_dates": false,
      "contains_money": false,
      "contains_email": false,
      "contains_phone": false,
      "text_length": 1,
      "word_count": 1,
      "analyzed_at": "2025-11-28T04:59:38.203804"
    },
    {
      "content_type": "other",
      "language": "korean",
      "text_preview": "학위 취득(예정)일",
      "keywords": [],
      "confidence_level": "high",
      "estimated_importance": "low",
      "contains_numbers": false,
      "contains_dates": false,
      "contains_money": false,
      "contains_email": false,
      "contains_phone": false,
      "text_length": 10,
      "word_count": 2,
      "analyzed_at": "2025-11-28T04:59:38.203816"
    },
    {
      "content_type": "other",
      "language": "korean",
      "text_preview": "학위 종류",
      "keywords": [],
      "confidence_level": "medium",
      "estimated_importance": "low",
      "contains_numbers": false,
      "contains_dates": false,
      "contains_money": false,
      "contains_email": false,
      "contains_phone": false,
      "text_length": 5,
      "word_count": 2,
      "analyzed_at": "2025-11-28T04:59:38.203825"
    },
    {
      "content_type": "other",
      "language": "korean",
      "text_preview": "전 공 분 야",
      "keywords": [],
      "confidence_level": "high",
      "estimated_importance": "low",
      "contains_numbers": false,
      "contains_dates": false,
      "contains_money": false,
      "contains_email": false,
      "contains_phone": false,
      "text_length": 7,
      "word_count": 4,
      "analyzed_at": "2025-11-28T04:59:38.203835"
    },
    {
      "content_type": "other",
      "language": "korean",
      "text_preview": "학",
      "keywords": [],
      "confidence_level": "high",
      "estimated_importance": "low",
      "contains_numbers": false,
      "contains_dates": false,
      "contains_money": false,
      "contains_email": false,
      "contains_phone": false,
      "text_length": 1,
      "word_count": 1,
      "analyzed_at": "2025-11-28T04:59:38.203844"
    },
    {
      "content_type": "other",
      "language": "korean",
      "text_preview": "위",
      "keywords": [],
      "confidence_level": "high",
      "estimated_importance": "low",
      "contains_numbers": false,
      "contains_dates": false,
      "contains_money": false,
      "contains_email": false,
      "contains_phone": false,
      "text_length": 1,
      "word_count": 1,
      "analyzed_at": "2025-11-28T04:59:38.203852"
    },
    {
      "content_type": "address",
      "language": "korean",
      "text_preview": "※서식변경 금지, 필요시 줄 추가 및 삭제 가능",
      "keywords": [
        "서식변경",
        "필요시"
      ],
      "confidence_level": "high",
      "estimated_importance": "important",
      "contains_numbers": false,
      "contains_dates": false,
      "contains_money": false,
      "contains_email": false,
      "contains_phone": false,
      "text_length": 26,
      "word_count": 8,
      "analyzed_at": "2025-11-28T04:59:38.203868"
    },
    {
      "content_type": "other",
      "language": "korean",
      "text_preview": "※학위, 근무경력, 자격증 등 : 증빙자료에 따라 증명...",
      "keywords": [
        "근무경력",
        "자격증",
        "증빙자료에",
        "증명이",
        "가능한"
      ],
      "confidence_level": "high",
      "estimated_importance": "low",
      "contains_numbers": false,
      "contains_dates": false,
      "contains_money": false,
      "contains_email": false,
      "contains_phone": false,
      "text_length": 41,
      "word_count": 11,
      "analyzed_at": "2025-11-28T04:59:38.203892"
    },
    {
      "content_type": "other",
      "language": "korean",
      "text_preview": "※근무경력은 임용분야와 관련된 경력만 작성",
      "keywords": [
        "근무경력은",
        "임용분야와",
        "관련된",
        "경력만"
      ],
      "confidence_level": "high",
      "estimated_importance": "low",
      "contains_numbers": false,
      "contains_dates": false,
      "contains_money": false,
      "contains_email": false,
      "contains_phone": false,
      "text_length": 23,
      "word_count": 5,
      "analyzed_at": "2025-11-28T04:59:38.203909"
    },
    {
      "content_type": "table",
      "language": "korean",
      "text_preview": "※비상근직(프리랜서 등)등 근무시간이 불분명한 응시자는...",
      "keywords": [
        "비상근직",
        "프리랜서",
        "근무시간이",
        "불분명한",
        "응시자는"
      ],
      "confidence_level": "high",
      "estimated_importance": "normal",
      "contains_numbers": false,
      "contains_dates": false,
      "contains_money": false,
      "contains_email": false,
      "contains_phone": false,
      "text_length": 48,
      "word_count": 10,
      "analyzed_at": "2025-11-28T04:59:38.203929"
    },
    {
      "content_type": "other",
      "language": "korean",
      "text_preview": "간과 근무기간을 각 직장별 인사업무 담당자의 확인을 필...",
      "keywords": [
        "근무기간을",
        "직장별",
        "인사업무",
        "담당자의",
        "확인을"
      ],
      "confidence_level": "high",
      "estimated_importance": "low",
      "contains_numbers": false,
      "contains_dates": false,
      "contains_money": false,
      "contains_email": false,
      "contains_phone": false,
      "text_length": 42,
      "word_count": 11,
      "analyzed_at": "2025-11-28T04:59:38.203952"
    }
  ],
  "insights": [
    "매우 높은 OCR 정확도로 신뢰할 수 있는 결과입니다."
  ],
  "recommendations": [
    "테이블 데이터를 스프레드시트 형태로 내보내기를 고려해보세요."
  ]
}